ado2hugo/__init__.py
ado2hugo/__main__.py
ado2hugo/_utils.py
ado2hugo/azure_devops.py
ado2hugo/hugo.py
ado2hugo/page.py
ado2hugo/project.py
ado2hugo/version.py
ado2hugo/wiki.py
ado2hugo-1.0.2.dist-info/METADATA
ado2hugo-1.0.2.dist-info/WHEEL
ado2hugo-1.0.2.dist-info/entry_points.txt
ado2hugo-1.0.2.dist-info/top_level.txt
ado2hugo-1.0.2.dist-info/RECORD
