Metadata-Version: 2.1
Name: ado2hugo
Version: 1.0.2
Summary: Azure DevOps Wiki to Hugo
Home-page: UNKNOWN
Author: panicoenlaxbox
Author-email: panicoenlaxbox@gmail.com
License: UNKNOWN
Project-URL: Source, https://github.com/panicoenlaxbox/ADO2Hugo/
Platform: UNKNOWN
Requires-Dist: requests
Requires-Dist: jsonpickle
